django_jinja/__init__.py
django_jinja/apps.py
django_jinja/backend.py
django_jinja/base.py
django_jinja/cache.py
django_jinja/jinja2.py
django_jinja/library.py
django_jinja/models.py
django_jinja/utils.py
django_jinja/builtins/__init__.py
django_jinja/builtins/extensions.py
django_jinja/builtins/filters.py
django_jinja/contrib/__init__.py
django_jinja/contrib/_easy_thumbnails/__init__.py
django_jinja/contrib/_easy_thumbnails/models.py
django_jinja/contrib/_easy_thumbnails/templatetags/__init__.py
django_jinja/contrib/_easy_thumbnails/templatetags/thumbnails.py
django_jinja/contrib/_humanize/__init__.py
django_jinja/contrib/_humanize/models.py
django_jinja/contrib/_humanize/templatetags/__init__.py
django_jinja/contrib/_humanize/templatetags/_humanize.py
django_jinja/contrib/_subdomains/__init__.py
django_jinja/contrib/_subdomains/models.py
django_jinja/contrib/_subdomains/templatetags/__init__.py
django_jinja/contrib/_subdomains/templatetags/subdomainurls.py
django_jinja/management/__init__.py
django_jinja/management/commands/__init__.py
django_jinja/management/commands/makemessages.py
django_jinja/views/__init__.py
django_jinja/views/generic/__init__.py
django_jinja/views/generic/base.py
django_jinja/views/generic/dates.py
django_jinja/views/generic/detail.py
django_jinja/views/generic/edit.py
django_jinja/views/generic/list.py
django_jinja-2.11.0.dist-info/LICENSE
django_jinja-2.11.0.dist-info/METADATA
django_jinja-2.11.0.dist-info/WHEEL
django_jinja-2.11.0.dist-info/top_level.txt
django_jinja-2.11.0.dist-info/RECORD
