Metadata-Version: 2.1
Name: django-jinja
Version: 2.11.0
Summary: Jinja2 templating language integrated in Django.
Home-page: https://github.com/niwinz/django-jinja
Author: Andrey Antukh
Author-email: niwi@niwi.be
Maintainer: Asif Saif Uddin
Maintainer-email: auvipy@gmail.com
License: BSD
Keywords: django,jinja2
Classifier: Development Status :: 5 - Production/Stable
Classifier: Framework :: Django
Classifier: Framework :: Django :: 3.2
Classifier: Framework :: Django :: 4.0
Classifier: Framework :: Django :: 4.1
Classifier: Framework :: Django :: 4.2
Classifier: Intended Audience :: Developers
Classifier: License :: OSI Approved :: BSD License
Classifier: Operating System :: OS Independent
Classifier: Programming Language :: Python
Classifier: Programming Language :: Python :: 3
Classifier: Programming Language :: Python :: 3 :: Only
Classifier: Programming Language :: Python :: 3.8
Classifier: Programming Language :: Python :: 3.9
Classifier: Programming Language :: Python :: 3.10
Classifier: Programming Language :: Python :: 3.11
Classifier: Topic :: Internet :: WWW/HTTP
Requires-Python: >=3.8
License-File: LICENSE
